tuya_tiny_web/__init__.py
tuya_tiny_web/main.py
tuya_tiny_web-1.6.0.dist-info/METADATA
tuya_tiny_web-1.6.0.dist-info/WHEEL
tuya_tiny_web-1.6.0.dist-info/entry_points.txt
tuya_tiny_web-1.6.0.dist-info/top_level.txt
tuya_tiny_web-1.6.0.dist-info/RECORD
