Metadata-Version: 2.4
Name: tuya-tiny-web
Version: 1.6.0
Summary: A tiny web interface for Tuya devices
Author-email: "@readwithai" <talwrii@github.com>
Project-URL: Homepage, https://github.com/talwrii/tuya-tiny-web
Requires-Dist: flask>=2.0
Requires-Dist: tinytuya>=0.5
